{
  "0": {
    "1": {
      "KNN": {
        "RMSE": 7.214441666523825,
        "R2": 0.0
      }
    },
    "2": {
      "KNN": {
        "RMSE": 8.3267183987878,
        "R2": -0.3321167912607168
      }
    },
    "3": {
      "KNN": {
        "RMSE": 9.497459719182807,
        "R2": -0.7330435174501957
      }
    },
    "4": {
      "KNN": {
        "RMSE": 8.868866078481219,
        "R2": -0.5112306099272648
      }
    },
    "5": {
      "KNN": {
        "RMSE": 8.788400061671899,
        "R2": -0.48393262974163753
      }
    },
    "6": {
      "KNN": {
        "RMSE": 7.894478345220258,
        "R2": -0.1974059811863753
      }
    },
    "7": {
      "KNN": {
        "RMSE": 8.963217064127237,
        "R2": -0.5435559475363649
      }
    },
    "8": {
      "KNN": {
        "RMSE": 8.297650268277936,
        "R2": -0.3228323278217331
      }
    },
    "9": {
      "KNN": {
        "RMSE": 8.32089043158726,
        "R2": -0.33025271571462733
      }
    },
    "10": {
      "KNN": {
        "RMSE": 7.850817707246455,
        "R2": -0.1841980299796213
      }
    },
    "11": {
      "KNN": {
        "RMSE": 7.986934054769662,
        "R2": -0.22561691142120766
      }
    },
    "12": {
      "KNN": {
        "RMSE": 8.592743516576576,
        "R2": -0.4185944133080124
      }
    },
    "13": {
      "KNN": {
        "RMSE": 8.042521156115964,
        "R2": -0.24273626405149096
      }
    },
    "14": {
      "KNN": {
        "RMSE": 8.204989047441801,
        "R2": -0.2934527214238676
      }
    },
    "15": {
      "KNN": {
        "RMSE": 8.152203675010382,
        "R2": -0.27686384743117043
      }
    },
    "16": {
      "KNN": {
        "RMSE": 8.269926447343368,
        "R2": -0.3140074922339642
      }
    },
    "17": {
      "KNN": {
        "RMSE": 8.379708837304882,
        "R2": -0.34912566841802284
      }
    },
    "18": {
      "KNN": {
        "RMSE": 8.062608286075806,
        "R2": -0.24895177243685263
      }
    },
    "19": {
      "KNN": {
        "RMSE": 8.204131949286653,
        "R2": -0.2931825058193023
      }
    },
    "20": {
      "KNN": {
        "RMSE": 7.907530862207318,
        "R2": -0.2013687717958692
      }
    },
    "21": {
      "KNN": {
        "RMSE": 7.834338790099105,
        "R2": -0.17923196870377422
      }
    },
    "22": {
      "KNN": {
        "RMSE": 7.740191262194012,
        "R2": -0.15105992070892849
      }
    },
    "23": {
      "KNN": {
        "RMSE": 7.750997560225984,
        "R2": -0.1542762183792814
      }
    },
    "24": {
      "KNN": {
        "RMSE": 7.739068463230049,
        "R2": -0.15072599739781922
      }
    },
    "25": {
      "KNN": {
        "RMSE": 7.877557427798578,
        "R2": -0.1922784748346189
      }
    },
    "26": {
      "KNN": {
        "RMSE": 7.831993731333301,
        "R2": -0.17852611350417646
      }
    },
    "27": {
      "KNN": {
        "RMSE": 7.530674348357528,
        "R2": -0.08958792807452665
      }
    },
    "28": {
      "KNN": {
        "RMSE": 7.634606202235637,
        "R2": -0.11987056367577087
      }
    },
    "29": {
      "KNN": {
        "RMSE": 7.822888842460373,
        "R2": -0.17578757399169187
      }
    },
    "30": {
      "KNN": {
        "RMSE": 7.475000257886458,
        "R2": -0.07353688711139217
      }
    },
    "31": {
      "KNN": {
        "RMSE": 7.678745782596781,
        "R2": -0.132857090372825
      }
    },
    "32": {
      "KNN": {
        "RMSE": 7.585649310236507,
        "R2": -0.10555427885839164
      }
    },
    "33": {
      "KNN": {
        "RMSE": 7.62987659095315,
        "R2": -0.11848348182375101
      }
    },
    "34": {
      "KNN": {
        "RMSE": 7.661770168246329,
        "R2": -0.12785375039132507
      }
    },
    "35": {
      "KNN": {
        "RMSE": 7.583617625162796,
        "R2": -0.10496215094948247
      }
    },
    "36": {
      "KNN": {
        "RMSE": 7.59984169709641,
        "R2": -0.1096950271113597
      }
    },
    "37": {
      "KNN": {
        "RMSE": 7.675539646631705,
        "R2": -0.1319112755997991
      }
    },
    "38": {
      "KNN": {
        "RMSE": 7.6375522529035065,
        "R2": -0.12073500432491668
      }
    },
    "39": {
      "KNN": {
        "RMSE": 7.725118339876136,
        "R2": -0.1465812345859645
      }
    },
    "40": {
      "KNN": {
        "RMSE": 7.738131869135333,
        "R2": -0.15044748895390692
      }
    },
    "41": {
      "KNN": {
        "RMSE": 7.7075345652241705,
        "R2": -0.14136752008889908
      }
    },
    "42": {
      "KNN": {
        "RMSE": 7.732636749915515,
        "R2": -0.14881412277914086
      }
    },
    "43": {
      "KNN": {
        "RMSE": 7.7217755835377755,
        "R2": -0.1455891688899109
      }
    },
    "44": {
      "KNN": {
        "RMSE": 7.7816333618098295,
        "R2": -0.16341879941855475
      }
    },
    "45": {
      "KNN": {
        "RMSE": 7.784180026779078,
        "R2": -0.1641804191406615
      }
    },
    "46": {
      "KNN": {
        "RMSE": 7.789957478533352,
        "R2": -0.16590917983563602
      }
    },
    "47": {
      "KNN": {
        "RMSE": 7.802025629601106,
        "R2": -0.16952441573733923
      }
    },
    "48": {
      "KNN": {
        "RMSE": 7.756401576146499,
        "R2": -0.15588630830439865
      }
    },
    "49": {
      "KNN": {
        "RMSE": 7.79068482064689,
        "R2": -0.16612691001930568
      }
    },
    "50": {
      "KNN": {
        "RMSE": 7.717331522701767,
        "R2": -0.14427092209790082
      }
    },
    "51": {
      "KNN": {
        "RMSE": 7.627376214785772,
        "R2": -0.11775052863152902
      }
    },
    "52": {
      "KNN": {
        "RMSE": 7.787323089982747,
        "R2": -0.16512074460890536
      }
    },
    "53": {
      "KNN": {
        "RMSE": 7.728610518283212,
        "R2": -0.1476181044647844
      }
    },
    "54": {
      "KNN": {
        "RMSE": 7.627134866374106,
        "R2": -0.11767979315471822
      }
    },
    "55": {
      "KNN": {
        "RMSE": 7.634232918759787,
        "R2": -0.11976105731854436
      }
    },
    "56": {
      "KNN": {
        "RMSE": 7.5975813897234055,
        "R2": -0.10903504524447749
      }
    },
    "57": {
      "KNN": {
        "RMSE": 7.5961046484157055,
        "R2": -0.10860396103134118
      }
    },
    "58": {
      "KNN": {
        "RMSE": 7.677308024000833,
        "R2": -0.13243290064682234
      }
    },
    "59": {
      "KNN": {
        "RMSE": 7.6319619569978,
        "R2": -0.11909496385602147
      }
    },
    "60": {
      "KNN": {
        "RMSE": 7.560256106959486,
        "R2": -0.09816491116849058
      }
    },
    "61": {
      "KNN": {
        "RMSE": 7.622103935660581,
        "R2": -0.11620581499237304
      }
    },
    "62": {
      "KNN": {
        "RMSE": 7.647129047377488,
        "R2": -0.12354736555613388
      }
    },
    "63": {
      "KNN": {
        "RMSE": 7.662153432768668,
        "R2": -0.1279665904089824
      }
    },
    "64": {
      "KNN": {
        "RMSE": 7.641988968247874,
        "R2": -0.12203747042250956
      }
    },
    "65": {
      "KNN": {
        "RMSE": 7.667546086906145,
        "R2": -0.12955488390381076
      }
    },
    "66": {
      "KNN": {
        "RMSE": 7.605071807927196,
        "R2": -0.11122290763058684
      }
    },
    "67": {
      "KNN": {
        "RMSE": 7.648174890764549,
        "R2": -0.1238547057165944
      }
    },
    "68": {
      "KNN": {
        "RMSE": 7.606687190503584,
        "R2": -0.11169502434712641
      }
    },
    "69": {
      "KNN": {
        "RMSE": 7.631350046156975,
        "R2": -0.1189155188084805
      }
    },
    "70": {
      "KNN": {
        "RMSE": 7.649933654815121,
        "R2": -0.12437164539182755
      }
    },
    "71": {
      "KNN": {
        "RMSE": 7.678823698668538,
        "R2": -0.13288008064354595
      }
    },
    "72": {
      "KNN": {
        "RMSE": 7.676165082689046,
        "R2": -0.1320957491354693
      }
    },
    "73": {
      "KNN": {
        "RMSE": 7.677955592646809,
        "R2": -0.13262394650960685
      }
    },
    "74": {
      "KNN": {
        "RMSE": 7.679519734449014,
        "R2": -0.13308546647851593
      }
    },
    "75": {
      "KNN": {
        "RMSE": 7.661718869316734,
        "R2": -0.12783864748555462
      }
    },
    "76": {
      "KNN": {
        "RMSE": 7.657811840466796,
        "R2": -0.1266886771771467
      }
    },
    "77": {
      "KNN": {
        "RMSE": 7.6465499826147,
        "R2": -0.12337721488869025
      }
    },
    "78": {
      "KNN": {
        "RMSE": 7.6838352709367514,
        "R2": -0.13435930801674
      }
    },
    "79": {
      "KNN": {
        "RMSE": 7.681829934809144,
        "R2": -0.13376729249699193
      }
    },
    "80": {
      "KNN": {
        "RMSE": 7.629431822904229,
        "R2": -0.11835308621101492
      }
    },
    "81": {
      "KNN": {
        "RMSE": 7.625560201629367,
        "R2": -0.11721833827838957
      }
    },
    "82": {
      "KNN": {
        "RMSE": 7.6411906982041415,
        "R2": -0.12180307015755631
      }
    },
    "83": {
      "KNN": {
        "RMSE": 7.644040997558022,
        "R2": -0.12264013104234794
      }
    },
    "84": {
      "KNN": {
        "RMSE": 7.641736973177728,
        "R2": -0.12196347312928513
      }
    },
    "85": {
      "KNN": {
        "RMSE": 7.64503477776279,
        "R2": -0.12293205256956363
      }
    },
    "86": {
      "KNN": {
        "RMSE": 7.644443722689897,
        "R2": -0.12275842640596069
      }
    },
    "87": {
      "KNN": {
        "RMSE": 7.6232523152442315,
        "R2": -0.11654218524993443
      }
    },
    "88": {
      "KNN": {
        "RMSE": 7.6130833535625175,
        "R2": -0.11356537131251043
      }
    },
    "89": {
      "KNN": {
        "RMSE": 7.609129022783803,
        "R2": -0.11240887215825301
      }
    },
    "90": {
      "KNN": {
        "RMSE": 7.594185588264385,
        "R2": -0.1080438821373686
      }
    },
    "91": {
      "KNN": {
        "RMSE": 7.60028468842703,
        "R2": -0.10982439812285638
      }
    },
    "92": {
      "KNN": {
        "RMSE": 7.615791455908941,
        "R2": -0.11435774024202683
      }
    },
    "93": {
      "KNN": {
        "RMSE": 7.6209080411101136,
        "R2": -0.11585558105599869
      }
    },
    "94": {
      "KNN": {
        "RMSE": 7.628036866476401,
        "R2": -0.11794416684632658
      }
    },
    "95": {
      "KNN": {
        "RMSE": 7.627030855528142,
        "R2": -0.11764930987883937
      }
    },
    "96": {
      "KNN": {
        "RMSE": 7.622760231991715,
        "R2": -0.11639804362786088
      }
    },
    "97": {
      "KNN": {
        "RMSE": 7.614284541542052,
        "R2": -0.11391679446113812
      }
    },
    "98": {
      "KNN": {
        "RMSE": 7.629121894251008,
        "R2": -0.11826222685641108
      }
    },
    "99": {
      "KNN": {
        "RMSE": 7.615623655521981,
        "R2": -0.11430863501084643
      }
    },
    "100": {
      "KNN": {
        "RMSE": 7.62713492167014,
        "R2": -0.11767980936087219
      }
    },
    "101": {
      "KNN": {
        "RMSE": 7.627565918655639,
        "R2": -0.11780612946509139
      }
    },
    "102": {
      "KNN": {
        "RMSE": 7.629193133951175,
        "R2": -0.11828311131436142
      }
    },
    "103": {
      "KNN": {
        "RMSE": 7.623936982698367,
        "R2": -0.11674275434906378
      }
    },
    "104": {
      "KNN": {
        "RMSE": 7.618747651329463,
        "R2": -0.11522302092315129
      }
    },
    "105": {
      "KNN": {
        "RMSE": 7.6185608986783535,
        "R2": -0.11516834834107503
      }
    },
    "106": {
      "KNN": {
        "RMSE": 7.604208493145213,
        "R2": -0.11097063369145332
      }
    },
    "107": {
      "KNN": {
        "RMSE": 7.607884619469121,
        "R2": -0.11204505335847603
      }
    },
    "108": {
      "KNN": {
        "RMSE": 7.612170199126993,
        "R2": -0.11329825321405762
      }
    },
    "109": {
      "KNN": {
        "RMSE": 7.6153652099640485,
        "R2": -0.1142330054253271
      }
    },
    "110": {
      "KNN": {
        "RMSE": 7.615661658986775,
        "R2": -0.1143197562785343
      }
    },
    "111": {
      "KNN": {
        "RMSE": 7.613266671149222,
        "R2": -0.11361899966905198
      }
    },
    "112": {
      "KNN": {
        "RMSE": 7.61695601479644,
        "R2": -0.11469856743996543
      }
    },
    "113": {
      "KNN": {
        "RMSE": 7.608122541272955,
        "R2": -0.11211460854112731
      }
    },
    "114": {
      "KNN": {
        "RMSE": 7.6134738584321155,
        "R2": -0.11367961250298952
      }
    },
    "115": {
      "KNN": {
        "RMSE": 7.6183141828618215,
        "R2": -0.11509612335831099
      }
    },
    "116": {
      "KNN": {
        "RMSE": 7.619079856827795,
        "R2": -0.11532027871763129
      }
    },
    "117": {
      "KNN": {
        "RMSE": 7.616317809000099,
        "R2": -0.11451177962551173
      }
    },
    "118": {
      "KNN": {
        "RMSE": 7.6149116847606395,
        "R2": -0.11410029538734134
      }
    },
    "119": {
      "KNN": {
        "RMSE": 7.617054387167102,
        "R2": -0.11472736010951423
      }
    },
    "120": {
      "KNN": {
        "RMSE": 7.62201091968474,
        "R2": -0.11617857203150939
      }
    },
    "121": {
      "KNN": {
        "RMSE": 7.62420496226169,
        "R2": -0.11682126221078049
      }
    },
    "122": {
      "KNN": {
        "RMSE": 7.621931906620709,
        "R2": -0.11615543057112832
      }
    },
    "123": {
      "KNN": {
        "RMSE": 7.614084368442815,
        "R2": -0.1138582273705877
      }
    },
    "124": {
      "KNN": {
        "RMSE": 7.642936865202625,
        "R2": -0.12231583823163827
      }
    },
    "125": {
      "KNN": {
        "RMSE": 7.636059802910509,
        "R2": -0.12029704266677288
      }
    },
    "126": {
      "KNN": {
        "RMSE": 7.64434083617384,
        "R2": -0.12272820421329667
      }
    },
    "127": {
      "KNN": {
        "RMSE": 7.634036281894204,
        "R2": -0.11970337412465737
      }
    },
    "128": {
      "KNN": {
        "RMSE": 7.635478165520388,
        "R2": -0.12012638349214844
      }
    },
    "129": {
      "KNN": {
        "RMSE": 7.634003403932783,
        "R2": -0.11969372955821722
      }
    },
    "130": {
      "KNN": {
        "RMSE": 7.635601277085271,
        "R2": -0.12016250477248658
      }
    },
    "131": {
      "KNN": {
        "RMSE": 7.643471414484921,
        "R2": -0.1224728339300638
      }
    },
    "132": {
      "KNN": {
        "RMSE": 7.641678741727163,
        "R2": -0.12194637405565212
      }
    },
    "133": {
      "KNN": {
        "RMSE": 7.638138351956213,
        "R2": -0.12090701936484427
      }
    },
    "134": {
      "KNN": {
        "RMSE": 7.642596643879142,
        "R2": -0.12221592185447228
      }
    },
    "135": {
      "KNN": {
        "RMSE": 7.627660390633964,
        "R2": -0.11783381903513979
      }
    },
    "136": {
      "KNN": {
        "RMSE": 7.63728961594628,
        "R2": -0.12065792691563249
      }
    },
    "137": {
      "KNN": {
        "RMSE": 7.634058726793197,
        "R2": -0.11970995823433439
      }
    },
    "138": {
      "KNN": {
        "RMSE": 7.634447885427196,
        "R2": -0.11982411923828229
      }
    },
    "139": {
      "KNN": {
        "RMSE": 7.645667910566892,
        "R2": -0.12311805422413946
      }
    },
    "140": {
      "KNN": {
        "RMSE": 7.641965148640189,
        "R2": -0.12203047579040205
      }
    },
    "141": {
      "KNN": {
        "RMSE": 7.6398194410245255,
        "R2": -0.1214004778004174
      }
    },
    "142": {
      "KNN": {
        "RMSE": 7.617526798798111,
        "R2": -0.11486563574043362
      }
    },
    "143": {
      "KNN": {
        "RMSE": 7.623073443191426,
        "R2": -0.1164897887552716
      }
    },
    "144": {
      "KNN": {
        "RMSE": 7.625110326020939,
        "R2": -0.11708651990951324
      }
    },
    "145": {
      "KNN": {
        "RMSE": 7.62715127899291,
        "R2": -0.11768460336784536
      }
    },
    "146": {
      "KNN": {
        "RMSE": 7.626805191401506,
        "R2": -0.1175831741494826
      }
    },
    "147": {
      "KNN": {
        "RMSE": 7.6277052445660045,
        "R2": -0.11784696576349529
      }
    },
    "148": {
      "KNN": {
        "RMSE": 7.623800403055563,
        "R2": -0.11670274274859183
      }
    },
    "149": {
      "KNN": {
        "RMSE": 7.622363142156262,
        "R2": -0.11628173437626521
      }
    },
    "150": {
      "KNN": {
        "RMSE": 7.612212839483725,
        "R2": -0.11331072575904333
      }
    },
    "151": {
      "KNN": {
        "RMSE": 7.619078614043097,
        "R2": -0.11531991486716953
      }
    },
    "152": {
      "KNN": {
        "RMSE": 7.634471784080805,
        "R2": -0.11983113017896008
      }
    },
    "153": {
      "KNN": {
        "RMSE": 7.637715438188878,
        "R2": -0.12078289647917062
      }
    },
    "154": {
      "KNN": {
        "RMSE": 7.626377221070172,
        "R2": -0.1174577536070962
      }
    },
    "155": {
      "KNN": {
        "RMSE": 7.626108485693892,
        "R2": -0.11737900189307737
      }
    },
    "156": {
      "KNN": {
        "RMSE": 7.626163765035778,
        "R2": -0.11739520103313583
      }
    },
    "157": {
      "KNN": {
        "RMSE": 7.627300898263754,
        "R2": -0.11772845428661993
      }
    },
    "158": {
      "KNN": {
        "RMSE": 7.627721788072143,
        "R2": -0.11785181469973538
      }
    },
    "159": {
      "KNN": {
        "RMSE": 7.625151798193552,
        "R2": -0.11709867137460206
      }
    },
    "160": {
      "KNN": {
        "RMSE": 7.621476641601201,
        "R2": -0.11602209656760598
      }
    },
    "161": {
      "KNN": {
        "RMSE": 7.620283411114724,
        "R2": -0.11567267153948757
      }
    },
    "162": {
      "KNN": {
        "RMSE": 7.617394478432954,
        "R2": -0.1148269044958512
      }
    },
    "163": {
      "KNN": {
        "RMSE": 7.615290154867498,
        "R2": -0.11421104234111956
      }
    },
    "164": {
      "KNN": {
        "RMSE": 7.62228097619447,
        "R2": -0.11625766838353524
      }
    },
    "165": {
      "KNN": {
        "RMSE": 7.62367233213798,
        "R2": -0.1166652244673907
      }
    },
    "166": {
      "KNN": {
        "RMSE": 7.623778259082152,
        "R2": -0.1166962556427853
      }
    },
    "167": {
      "KNN": {
        "RMSE": 7.633152424181425,
        "R2": -0.11944411384972864
      }
    },
    "168": {
      "KNN": {
        "RMSE": 7.631470279285882,
        "R2": -0.11895077646872942
      }
    },
    "169": {
      "KNN": {
        "RMSE": 7.6317752014822,
        "R2": -0.11904019560611179
      }
    },
    "170": {
      "KNN": {
        "RMSE": 7.625326543725462,
        "R2": -0.1171498730407412
      }
    },
    "171": {
      "KNN": {
        "RMSE": 7.610963298670438,
        "R2": -0.1129452569938807
      }
    },
    "172": {
      "KNN": {
        "RMSE": 7.616423616550341,
        "R2": -0.11454274592266112
      }
    },
    "173": {
      "KNN": {
        "RMSE": 7.625739714239331,
        "R2": -0.11727093956540924
      }
    },
    "174": {
      "KNN": {
        "RMSE": 7.625118922531825,
        "R2": -0.11708903870633858
      }
    },
    "175": {
      "KNN": {
        "RMSE": 7.6235169694412575,
        "R2": -0.11661971192558784
      }
    },
    "176": {
      "KNN": {
        "RMSE": 7.6148115347356935,
        "R2": -0.11407099066437842
      }
    },
    "177": {
      "KNN": {
        "RMSE": 7.619042098264353,
        "R2": -0.11530922415777844
      }
    },
    "178": {
      "KNN": {
        "RMSE": 7.622040752696114,
        "R2": -0.11618730962938284
      }
    },
    "179": {
      "KNN": {
        "RMSE": 7.626218099050413,
        "R2": -0.11741112326752678
      }
    },
    "180": {
      "KNN": {
        "RMSE": 7.626925816876648,
        "R2": -0.1176185257978013
      }
    },
    "181": {
      "KNN": {
        "RMSE": 7.625197279398922,
        "R2": -0.11711199757372781
      }
    },
    "182": {
      "KNN": {
        "RMSE": 7.6245849637863605,
        "R2": -0.11693259299496828
      }
    },
    "183": {
      "KNN": {
        "RMSE": 7.627364366369056,
        "R2": -0.11774705599208168
      }
    },
    "184": {
      "KNN": {
        "RMSE": 7.625208807084684,
        "R2": -0.11711537525048366
      }
    },
    "185": {
      "KNN": {
        "RMSE": 7.627730007539878,
        "R2": -0.11785422384682498
      }
    },
    "186": {
      "KNN": {
        "RMSE": 7.625935481956504,
        "R2": -0.11732830538093841
      }
    },
    "187": {
      "KNN": {
        "RMSE": 7.612959791034733,
        "R2": -0.1135292246347086
      }
    },
    "188": {
      "KNN": {
        "RMSE": 7.603713787520241,
        "R2": -0.11082608595990817
      }
    },
    "189": {
      "KNN": {
        "RMSE": 7.607641689247768,
        "R2": -0.11197403623575175
      }
    },
    "190": {
      "KNN": {
        "RMSE": 7.610437797465326,
        "R2": -0.11279157503271176
      }
    },
    "191": {
      "KNN": {
        "RMSE": 7.606710091465968,
        "R2": -0.11170171817418151
      }
    },
    "192": {
      "KNN": {
        "RMSE": 7.611588676544721,
        "R2": -0.11312816155054173
      }
    },
    "193": {
      "KNN": {
        "RMSE": 7.606155776954022,
        "R2": -0.11153970070935038
      }
    },
    "194": {
      "KNN": {
        "RMSE": 7.603623888672447,
        "R2": -0.11079981948074247
      }
    },
    "195": {
      "KNN": {
        "RMSE": 7.604393065229593,
        "R2": -0.11102456610382849
      }
    },
    "196": {
      "KNN": {
        "RMSE": 7.605309605215698,
        "R2": -0.11129240070896462
      }
    },
    "197": {
      "KNN": {
        "RMSE": 7.601271797668539,
        "R2": -0.11011270023430408
      }
    },
    "198": {
      "KNN": {
        "RMSE": 7.598573317784876,
        "R2": -0.10932465182810858
      }
    },
    "199": {
      "KNN": {
        "RMSE": 7.594047400232303,
        "R2": -0.10800355733660072
      }
    },
    "200": {
      "KNN": {
        "RMSE": 7.593514242234483,
        "R2": -0.10784798279514907
      }
    },
    "201": {
      "KNN": {
        "RMSE": 7.594618330508685,
        "R2": -0.10817016587179995
      }
    },
    "202": {
      "KNN": {
        "RMSE": 7.60180175989472,
        "R2": -0.11026750019999598
      }
    },
    "203": {
      "KNN": {
        "RMSE": 7.599621183259293,
        "R2": -0.10963063114941507
      }
    },
    "204": {
      "KNN": {
        "RMSE": 7.60279368413674,
        "R2": -0.1105572665304626
      }
    },
    "205": {
      "KNN": {
        "RMSE": 7.605507146466986,
        "R2": -0.11135013115092618
      }
    },
    "206": {
      "KNN": {
        "RMSE": 7.614435096913164,
        "R2": -0.1139608453009695
      }
    },
    "207": {
      "KNN": {
        "RMSE": 7.61541936684758,
        "R2": -0.11424885328029033
      }
    },
    "208": {
      "KNN": {
        "RMSE": 7.616158369928008,
        "R2": -0.11446511800542347
      }
    },
    "209": {
      "KNN": {
        "RMSE": 7.61732258286228,
        "R2": -0.1148058603610147
      }
    },
    "210": {
      "KNN": {
        "RMSE": 7.6138441341376515,
        "R2": -0.11378794111606338
      }
    },
    "211": {
      "KNN": {
        "RMSE": 7.613988539987068,
        "R2": -0.11383019021287022
      }
    },
    "212": {
      "KNN": {
        "RMSE": 7.6145388047827955,
        "R2": -0.11399118958557586
      }
    },
    "213": {
      "KNN": {
        "RMSE": 7.605696840074392,
        "R2": -0.1114055695695495
      }
    },
    "214": {
      "KNN": {
        "RMSE": 7.6083597487586925,
        "R2": -0.1121839570620391
      }
    },
    "215": {
      "KNN": {
        "RMSE": 7.610681285061666,
        "R2": -0.11286278125958904
      }
    },
    "216": {
      "KNN": {
        "RMSE": 7.608366551357803,
        "R2": -0.11218594585994812
      }
    },
    "217": {
      "KNN": {
        "RMSE": 7.618879378073414,
        "R2": -0.11526158525787533
      }
    },
    "218": {
      "KNN": {
        "RMSE": 7.614425810064872,
        "R2": -0.11395812804645655
      }
    },
    "219": {
      "KNN": {
        "RMSE": 7.596271644365997,
        "R2": -0.10865270559597029
      }
    },
    "220": {
      "KNN": {
        "RMSE": 7.5887519456727635,
        "R2": -0.10645883777685938
      }
    },
    "221": {
      "KNN": {
        "RMSE": 7.584427936609757,
        "R2": -0.10519829453122354
      }
    },
    "222": {
      "KNN": {
        "RMSE": 7.5844077131251195,
        "R2": -0.10519240063095325
      }
    },
    "223": {
      "KNN": {
        "RMSE": 7.582222328939264,
        "R2": -0.10455558834026446
      }
    },
    "224": {
      "KNN": {
        "RMSE": 7.576977067371729,
        "R2": -0.10302788874605295
      }
    },
    "225": {
      "KNN": {
        "RMSE": 7.582554895212534,
        "R2": -0.10465248499553548
      }
    },
    "226": {
      "KNN": {
        "RMSE": 7.583273463737734,
        "R2": -0.10486186194805636
      }
    },
    "227": {
      "KNN": {
        "RMSE": 7.585355412846262,
        "R2": -0.1054686136213836
      }
    },
    "228": {
      "KNN": {
        "RMSE": 7.58287290304524,
        "R2": -0.10474514387210387
      }
    },
    "229": {
      "KNN": {
        "RMSE": 7.57581626935118,
        "R2": -0.10268994539477294
      }
    },
    "230": {
      "KNN": {
        "RMSE": 7.552255023187028,
        "R2": -0.09584174647488819
      }
    },
    "231": {
      "KNN": {
        "RMSE": 7.554684406686861,
        "R2": -0.09654687309892762
      }
    },
    "232": {
      "KNN": {
        "RMSE": 7.551954823177566,
        "R2": -0.09575462940498425
      }
    },
    "233": {
      "KNN": {
        "RMSE": 7.5318503592078025,
        "R2": -0.0899282607505616
      }
    },
    "234": {
      "KNN": {
        "RMSE": 7.517659045864483,
        "R2": -0.0858249020822206
      }
    },
    "235": {
      "KNN": {
        "RMSE": 7.515463097953429,
        "R2": -0.08519064435362278
      }
    },
    "236": {
      "KNN": {
        "RMSE": 7.51110672579941,
        "R2": -0.08393293765303866
      }
    },
    "237": {
      "KNN": {
        "RMSE": 7.5066749135948,
        "R2": -0.08265419932664941
      }
    },
    "238": {
      "KNN": {
        "RMSE": 7.509759689161718,
        "R2": -0.08354418896214821
      }
    },
    "239": {
      "KNN": {
        "RMSE": 7.513344423197398,
        "R2": -0.08457888113525303
      }
    },
    "240": {
      "KNN": {
        "RMSE": 7.510185448757395,
        "R2": -0.08366705372273375
      }
    },
    "241": {
      "KNN": {
        "RMSE": 7.488801932967848,
        "R2": -0.07750485642780691
      }
    },
    "242": {
      "KNN": {
        "RMSE": 7.483780055259797,
        "R2": -0.07606022393065293
      }
    },
    "243": {
      "KNN": {
        "RMSE": 7.481608677271719,
        "R2": -0.07543588850106753
      }
    },
    "244": {
      "KNN": {
        "RMSE": 7.4810096455822634,
        "R2": -0.07526368104822811
      }
    },
    "245": {
      "KNN": {
        "RMSE": 7.484844881697992,
        "R2": -0.07636645925107577
      }
    },
    "246": {
      "KNN": {
        "RMSE": 7.4849679973278755,
        "R2": -0.07640186910300417
      }
    },
    "247": {
      "KNN": {
        "RMSE": 7.489838574187498,
        "R2": -0.07780318539102948
      }
    },
    "248": {
      "KNN": {
        "RMSE": 7.491866536461111,
        "R2": -0.07838692029659011
      }
    },
    "249": {
      "KNN": {
        "RMSE": 7.491024449891151,
        "R2": -0.07814451231898167
      }
    },
    "250": {
      "KNN": {
        "RMSE": 7.4935791797688704,
        "R2": -0.07888001590456062
      }
    },
    "251": {
      "KNN": {
        "RMSE": 7.4912138508383235,
        "R2": -0.07819903201109457
      }
    },
    "252": {
      "KNN": {
        "RMSE": 7.494897366734883,
        "R2": -0.07925961839530604
      }
    },
    "253": {
      "KNN": {
        "RMSE": 7.4933889607019335,
        "R2": -0.07882524342793396
      }
    },
    "254": {
      "KNN": {
        "RMSE": 7.490869616897375,
        "R2": -0.07809994415116717
      }
    },
    "255": {
      "KNN": {
        "RMSE": 7.490634156485287,
        "R2": -0.07803216941192459
      }
    },
    "256": {
      "KNN": {
        "RMSE": 7.489331477690825,
        "R2": -0.07765724587256839
      }
    },
    "257": {
      "KNN": {
        "RMSE": 7.489887339184477,
        "R2": -0.07781722020357185
      }
    },
    "258": {
      "KNN": {
        "RMSE": 7.4921264613215595,
        "R2": -0.0784617492943569
      }
    },
    "259": {
      "KNN": {
        "RMSE": 7.490964229270921,
        "R2": -0.07812717790212309
      }
    },
    "260": {
      "KNN": {
        "RMSE": 7.49293551512291,
        "R2": -0.07869468201208751
      }
    },
    "261": {
      "KNN": {
        "RMSE": 7.494067804042162,
        "R2": -0.07902071880186656
      }
    },
    "262": {
      "KNN": {
        "RMSE": 7.499114765948289,
        "R2": -0.08047456479446091
      }
    },
    "263": {
      "KNN": {
        "RMSE": 7.494854224220961,
        "R2": -0.07924719345155506
      }
    },
    "264": {
      "KNN": {
        "RMSE": 7.5072409987074575,
        "R2": -0.08281749333902
      }
    },
    "265": {
      "KNN": {
        "RMSE": 7.50967044122365,
        "R2": -0.08351843487305777
      }
    },
    "266": {
      "KNN": {
        "RMSE": 7.508519325371496,
        "R2": -0.08318628723387267
      }
    },
    "267": {
      "KNN": {
        "RMSE": 7.507913316902384,
        "R2": -0.08301144754961687
      }
    },
    "268": {
      "KNN": {
        "RMSE": 7.510052625206308,
        "R2": -0.08362872304916058
      }
    },
    "269": {
      "KNN": {
        "RMSE": 7.5152335036538265,
        "R2": -0.0851243411127156
      }
    },
    "270": {
      "KNN": {
        "RMSE": 7.514418733620315,
        "R2": -0.08488906462564794
      }
    },
    "271": {
      "KNN": {
        "RMSE": 7.514953523073171,
        "R2": -0.08504348984344778
      }
    },
    "272": {
      "KNN": {
        "RMSE": 7.51792949225577,
        "R2": -0.08590302818681828
      }
    },
    "273": {
      "KNN": {
        "RMSE": 7.521138366655312,
        "R2": -0.08683021700404048
      }
    },
    "274": {
      "KNN": {
        "RMSE": 7.540836813780428,
        "R2": -0.0925306581511951
      }
    },
    "275": {
      "KNN": {
        "RMSE": 7.558715457608728,
        "R2": -0.09771738276605757
      }
    },
    "276": {
      "KNN": {
        "RMSE": 7.562558025563372,
        "R2": -0.09883374329377204
      }
    },
    "277": {
      "KNN": {
        "RMSE": 7.561579142181151,
        "R2": -0.09854929973017268
      }
    },
    "278": {
      "KNN": {
        "RMSE": 7.566918613168628,
        "R2": -0.10010128853370137
      }
    },
    "279": {
      "KNN": {
        "RMSE": 7.5653038812243345,
        "R2": -0.09963182949746607
      }
    },
    "280": {
      "KNN": {
        "RMSE": 7.559840202261401,
        "R2": -0.09804409002791026
      }
    },
    "281": {
      "KNN": {
        "RMSE": 7.558898059411684,
        "R2": -0.09777042024193783
      }
    },
    "282": {
      "KNN": {
        "RMSE": 7.563044917404523,
        "R2": -0.09897523785293161
      }
    },
    "283": {
      "KNN": {
        "RMSE": 7.563201411989213,
        "R2": -0.09902071833193293
      }
    },
    "284": {
      "KNN": {
        "RMSE": 7.5662399744027615,
        "R2": -0.09990397231006232
      }
    },
    "285": {
      "KNN": {
        "RMSE": 7.561008826375481,
        "R2": -0.09838359455399104
      }
    },
    "286": {
      "KNN": {
        "RMSE": 7.559023216514835,
        "R2": -0.09780677339873356
      }
    },
    "287": {
      "KNN": {
        "RMSE": 7.562021628265396,
        "R2": -0.09867787260929162
      }
    },
    "288": {
      "KNN": {
        "RMSE": 7.560944938281652,
        "R2": -0.09836503265589291
      }
    },
    "289": {
      "KNN": {
        "RMSE": 7.573048955666782,
        "R2": -0.1018845056799782
      }
    },
    "290": {
      "KNN": {
        "RMSE": 7.577573738855179,
        "R2": -0.10320161797727856
      }
    },
    "291": {
      "KNN": {
        "RMSE": 7.575531020968244,
        "R2": -0.1026069089031254
      }
    },
    "292": {
      "KNN": {
        "RMSE": 7.5752777005721645,
        "R2": -0.10253316934662471
      }
    },
    "293": {
      "KNN": {
        "RMSE": 7.58174944810628,
        "R2": -0.10441781689116847
      }
    },
    "294": {
      "KNN": {
        "RMSE": 7.588516846012218,
        "R2": -0.10639028261267836
      }
    },
    "295": {
      "KNN": {
        "RMSE": 7.571091852861294,
        "R2": -0.10131505931359719
      }
    },
    "296": {
      "KNN": {
        "RMSE": 7.570750372004284,
        "R2": -0.10121571577466515
      }
    },
    "297": {
      "KNN": {
        "RMSE": 7.558108417379768,
        "R2": -0.09754107454080851
      }
    },
    "298": {
      "KNN": {
        "RMSE": 7.550293402110946,
        "R2": -0.09527255301211257
      }
    },
    "299": {
      "KNN": {
        "RMSE": 7.5498072233831275,
        "R2": -0.09513150390481084
      }
    },
    "300": {
      "KNN": {
        "RMSE": 7.547643585636291,
        "R2": -0.09450390421484411
      }
    },
    "301": {
      "KNN": {
        "RMSE": 7.5426789920132675,
        "R2": -0.09306451986547004
      }
    },
    "302": {
      "KNN": {
        "RMSE": 7.5496517313344205,
        "R2": -0.09508639480929015
      }
    },
    "303": {
      "KNN": {
        "RMSE": 7.549310591581419,
        "R2": -0.09498743155236955
      }
    },
    "304": {
      "KNN": {
        "RMSE": 7.555023356023236,
        "R2": -0.09664527090159214
      }
    },
    "305": {
      "KNN": {
        "RMSE": 7.556542311150363,
        "R2": -0.09708628142673192
      }
    },
    "306": {
      "KNN": {
        "RMSE": 7.560754098957929,
        "R2": -0.09830958757688912
      }
    },
    "307": {
      "KNN": {
        "RMSE": 7.562148102032201,
        "R2": -0.09871462338782111
      }
    },
    "308": {
      "KNN": {
        "RMSE": 7.56225706763087,
        "R2": -0.09874628713141509
      }
    },
    "309": {
      "KNN": {
        "RMSE": 7.561410289890367,
        "R2": -0.09850023841870348
      }
    },
    "310": {
      "KNN": {
        "RMSE": 7.569299412473982,
        "R2": -0.10079365290229259
      }
    },
    "311": {
      "KNN": {
        "RMSE": 7.570463832627134,
        "R2": -0.10113235925689423
      }
    },
    "312": {
      "KNN": {
        "RMSE": 7.5729990869830655,
        "R2": -0.10186999386332252
      }
    },
    "313": {
      "KNN": {
        "RMSE": 7.574024271865585,
        "R2": -0.10216834248523132
      }
    },
    "314": {
      "KNN": {
        "RMSE": 7.572530475954497,
        "R2": -0.10173363244306288
      }
    },
    "315": {
      "KNN": {
        "RMSE": 7.5748714763090375,
        "R2": -0.10241492583573941
      }
    },
    "316": {
      "KNN": {
        "RMSE": 7.574857364689342,
        "R2": -0.10241081834804455
      }
    },
    "317": {
      "KNN": {
        "RMSE": 7.570006318845458,
        "R2": -0.10099927150477828
      }
    },
    "318": {
      "KNN": {
        "RMSE": 7.569939500845463,
        "R2": -0.10097983526085863
      }
    },
    "319": {
      "KNN": {
        "RMSE": 7.5703375230932215,
        "R2": -0.10109561583987836
      }
    },
    "320": {
      "KNN": {
        "RMSE": 7.572073778524126,
        "R2": -0.10160074588742796
      }
    },
    "321": {
      "KNN": {
        "RMSE": 7.57344509076596,
        "R2": -0.10199978462421977
      }
    },
    "322": {
      "KNN": {
        "RMSE": 7.571774370877096,
        "R2": -0.10151363073877118
      }
    },
    "323": {
      "KNN": {
        "RMSE": 7.560791433010908,
        "R2": -0.09832043423293158
      }
    },
    "324": {
      "KNN": {
        "RMSE": 7.556186117850651,
        "R2": -0.09698285698826026
      }
    },
    "325": {
      "KNN": {
        "RMSE": 7.552734047791823,
        "R2": -0.09598076503443376
      }
    },
    "326": {
      "KNN": {
        "RMSE": 7.550260719624421,
        "R2": -0.09526307095596609
      }
    },
    "327": {
      "KNN": {
        "RMSE": 7.551591122574292,
        "R2": -0.09564908930772331
      }
    },
    "328": {
      "KNN": {
        "RMSE": 7.552511277555574,
        "R2": -0.09591611340186268
      }
    },
    "329": {
      "KNN": {
        "RMSE": 7.553933469809669,
        "R2": -0.09632889005282186
      }
    },
    "330": {
      "KNN": {
        "RMSE": 7.556634838350299,
        "R2": -0.09711314846168206
      }
    },
    "331": {
      "KNN": {
        "RMSE": 7.558048429195347,
        "R2": -0.09752365239455951
      }
    },
    "332": {
      "KNN": {
        "RMSE": 7.534189001000588,
        "R2": -0.0906052119339471
      }
    },
    "333": {
      "KNN": {
        "RMSE": 7.53290096894446,
        "R2": -0.09023234780806355
      }
    },
    "334": {
      "KNN": {
        "RMSE": 7.525381213428561,
        "R2": -0.08805677461049677
      }
    },
    "335": {
      "KNN": {
        "RMSE": 7.524285316182173,
        "R2": -0.0877398972147061
      }
    },
    "336": {
      "KNN": {
        "RMSE": 7.511238330892207,
        "R2": -0.0839709220273197
      }
    },
    "337": {
      "KNN": {
        "RMSE": 7.508977768316631,
        "R2": -0.0833185621205157
      }
    },
    "338": {
      "KNN": {
        "RMSE": 7.510724546715552,
        "R2": -0.08382263541047252
      }
    },
    "339": {
      "KNN": {
        "RMSE": 7.499033176017883,
        "R2": -0.08045105392211549
      }
    },
    "340": {
      "KNN": {
        "RMSE": 7.500442739863338,
        "R2": -0.08085726838723306
      }
    },
    "341": {
      "KNN": {
        "RMSE": 7.488411977990618,
        "R2": -0.07739264423530834
      }
    },
    "342": {
      "KNN": {
        "RMSE": 7.456650201818989,
        "R2": -0.06827259769069371
      }
    },
    "343": {
      "KNN": {
        "RMSE": 7.441537123387511,
        "R2": -0.06394665347856332
      }
    },
    "344": {
      "KNN": {
        "RMSE": 7.442495984593718,
        "R2": -0.06422085567114921
      }
    },
    "345": {
      "KNN": {
        "RMSE": 7.444909030659861,
        "R2": -0.06491106236047695
      }
    },
    "346": {
      "KNN": {
        "RMSE": 7.44772631211653,
        "R2": -0.06571717613072492
      }
    },
    "347": {
      "KNN": {
        "RMSE": 7.453222452208483,
        "R2": -0.0672906743762558
      }
    },
    "348": {
      "KNN": {
        "RMSE": 7.453746192180797,
        "R2": -0.0674406772593763
      }
    },
    "349": {
      "KNN": {
        "RMSE": 7.454112580345325,
        "R2": -0.06754561972255724
      }
    },
    "350": {
      "KNN": {
        "RMSE": 7.453089153908749,
        "R2": -0.06725249847021741
      }
    },
    "351": {
      "KNN": {
        "RMSE": 7.452878898061141,
        "R2": -0.06719228373002739
      }
    },
    "352": {
      "KNN": {
        "RMSE": 7.4514172970215915,
        "R2": -0.06677374576000239
      }
    },
    "353": {
      "KNN": {
        "RMSE": 7.449522009625415,
        "R2": -0.06623114141405506
      }
    },
    "354": {
      "KNN": {
        "RMSE": 7.453362314686933,
        "R2": -0.06733073096130804
      }
    },
    "355": {
      "KNN": {
        "RMSE": 7.448909094897891,
        "R2": -0.06605569877901774
      }
    },
    "356": {
      "KNN": {
        "RMSE": 7.453302458822017,
        "R2": -0.06731358816190247
      }
    },
    "357": {
      "KNN": {
        "RMSE": 7.455545620087788,
        "R2": -0.06795612663065853
      }
    },
    "358": {
      "KNN": {
        "RMSE": 7.45389367531841,
        "R2": -0.0674829193893669
      }
    },
    "359": {
      "KNN": {
        "RMSE": 7.457655128607024,
        "R2": -0.06856055758181401
      }
    },
    "360": {
      "KNN": {
        "RMSE": 7.456094387995395,
        "R2": -0.06811334694623672
      }
    },
    "361": {
      "KNN": {
        "RMSE": 7.458617542630837,
        "R2": -0.0688363718976508
      }
    },
    "362": {
      "KNN": {
        "RMSE": 7.456404944335091,
        "R2": -0.06820232550852845
      }
    },
    "363": {
      "KNN": {
        "RMSE": 7.45319671407254,
        "R2": -0.06728330306130759
      }
    },
    "364": {
      "KNN": {
        "RMSE": 7.429917613077868,
        "R2": -0.06062667073158878
      }
    },
    "365": {
      "KNN": {
        "RMSE": 7.430130843233829,
        "R2": -0.06068754915512642
      }
    },
    "366": {
      "KNN": {
        "RMSE": 7.41153440332799,
        "R2": -0.05538472787441551
      }
    },
    "367": {
      "KNN": {
        "RMSE": 7.413761499531207,
        "R2": -0.056019089488484
      }
    },
    "368": {
      "KNN": {
        "RMSE": 7.410435626212327,
        "R2": -0.055071824617140885
      }
    },
    "369": {
      "KNN": {
        "RMSE": 7.413711780131894,
        "R2": -0.056004925434585795
      }
    },
    "370": {
      "KNN": {
        "RMSE": 7.413420837516737,
        "R2": -0.05592204365683173
      }
    },
    "371": {
      "KNN": {
        "RMSE": 7.409377856098675,
        "R2": -0.05477064291900846
      }
    },
    "372": {
      "KNN": {
        "RMSE": 7.41015387147288,
        "R2": -0.054991595639869884
      }
    },
    "373": {
      "KNN": {
        "RMSE": 7.410338843777541,
        "R2": -0.0550442657101069
      }
    },
    "374": {
      "KNN": {
        "RMSE": 7.411595747308851,
        "R2": -0.05540219841828731
      }
    },
    "375": {
      "KNN": {
        "RMSE": 7.409897617440122,
        "R2": -0.054918630575684135
      }
    },
    "376": {
      "KNN": {
        "RMSE": 7.409910192908868,
        "R2": -0.05492221122098062
      }
    },
    "377": {
      "KNN": {
        "RMSE": 7.408976149267268,
        "R2": -0.05465627512857729
      }
    },
    "378": {
      "KNN": {
        "RMSE": 7.40902201850144,
        "R2": -0.05466933399782725
      }
    },
    "379": {
      "KNN": {
        "RMSE": 7.389815502355521,
        "R2": -0.049208351994987076
      }
    },
    "380": {
      "KNN": {
        "RMSE": 7.388448958760943,
        "R2": -0.04882034328695428
      }
    },
    "381": {
      "KNN": {
        "RMSE": 7.389745869016522,
        "R2": -0.049188578960974505
      }
    },
    "382": {
      "KNN": {
        "RMSE": 7.393407857113651,
        "R2": -0.05022868727758212
      }
    },
    "383": {
      "KNN": {
        "RMSE": 7.3940721451331965,
        "R2": -0.05041741910190156
      }
    },
    "384": {
      "KNN": {
        "RMSE": 7.391906233894647,
        "R2": -0.049802121433793145
      }
    },
    "385": {
      "KNN": {
        "RMSE": 7.375689996844386,
        "R2": -0.045201098040133614
      }
    },
    "386": {
      "KNN": {
        "RMSE": 7.373109217365269,
        "R2": -0.04446978703713422
      }
    },
    "387": {
      "KNN": {
        "RMSE": 7.3706457087541475,
        "R2": -0.043771945629340836
      }
    },
    "388": {
      "KNN": {
        "RMSE": 7.369381578715817,
        "R2": -0.04341394434369428
      }
    },
    "389": {
      "KNN": {
        "RMSE": 7.36724299104868,
        "R2": -0.04280843670659085
      }
    },
    "390": {
      "KNN": {
        "RMSE": 7.371822285997472,
        "R2": -0.04410520716059274
      }
    },
    "391": {
      "KNN": {
        "RMSE": 7.371193682494293,
        "R2": -0.04392715072284159
      }
    },
    "392": {
      "KNN": {
        "RMSE": 7.371731074334457,
        "R2": -0.044079369862990214
      }
    },
    "393": {
      "KNN": {
        "RMSE": 7.371048527191578,
        "R2": -0.04388603660317414
      }
    },
    "394": {
      "KNN": {
        "RMSE": 7.372588286473173,
        "R2": -0.044322202797999255
      }
    },
    "395": {
      "KNN": {
        "RMSE": 7.372044493358516,
        "R2": -0.04416815261706675
      }
    },
    "396": {
      "KNN": {
        "RMSE": 7.377570751469053,
        "R2": -0.04573420543178908
      }
    },
    "397": {
      "KNN": {
        "RMSE": 7.3770266754860785,
        "R2": -0.04557997095398503
      }
    },
    "398": {
      "KNN": {
        "RMSE": 7.377992738250102,
        "R2": -0.04585383793590814
      }
    },
    "399": {
      "KNN": {
        "RMSE": 7.375244931796285,
        "R2": -0.04507496246715892
      }
    },
    "400": {
      "KNN": {
        "RMSE": 7.372212003490456,
        "R2": -0.044215605052368545
      }
    },
    "401": {
      "KNN": {
        "RMSE": 7.356531458164845,
        "R2": -0.0397782783253966
      }
    },
    "402": {
      "KNN": {
        "RMSE": 7.356084813225723,
        "R2": -0.03965202382344768
      }
    },
    "403": {
      "KNN": {
        "RMSE": 7.351519823790517,
        "R2": -0.03836206374140949
      }
    },
    "404": {
      "KNN": {
        "RMSE": 7.352912627889475,
        "R2": -0.038755552971834195
      }
    },
    "405": {
      "KNN": {
        "RMSE": 7.3507716191493975,
        "R2": -0.03815071485062016
      }
    },
    "406": {
      "KNN": {
        "RMSE": 7.3501076734279795,
        "R2": -0.03796318498785123
      }
    },
    "407": {
      "KNN": {
        "RMSE": 7.349170491326379,
        "R2": -0.03769850900051708
      }
    },
    "408": {
      "KNN": {
        "RMSE": 7.346776912615444,
        "R2": -0.03702267529077252
      }
    },
    "409": {
      "KNN": {
        "RMSE": 7.3478449342030725,
        "R2": -0.03732420700243022
      }
    },
    "410": {
      "KNN": {
        "RMSE": 7.348296738304772,
        "R2": -0.037451776853023144
      }
    },
    "411": {
      "KNN": {
        "RMSE": 7.347793292975963,
        "R2": -0.03730962626285361
      }
    },
    "412": {
      "KNN": {
        "RMSE": 7.347429798884772,
        "R2": -0.03720699773796121
      }
    },
    "413": {
      "KNN": {
        "RMSE": 7.350635381992284,
        "R2": -0.03811223361389615
      }
    },
    "414": {
      "KNN": {
        "RMSE": 7.346892392660531,
        "R2": -0.03705527635322725
      }
    },
    "415": {
      "KNN": {
        "RMSE": 7.3492544799585815,
        "R2": -0.03772222742602627
      }
    },
    "416": {
      "KNN": {
        "RMSE": 7.348662473453483,
        "R2": -0.037555050315118965
      }
    },
    "417": {
      "KNN": {
        "RMSE": 7.349306023680765,
        "R2": -0.03773678352934495
      }
    },
    "418": {
      "KNN": {
        "RMSE": 7.351171161427129,
        "R2": -0.038263572764129616
      }
    },
    "419": {
      "KNN": {
        "RMSE": 7.351800944596526,
        "R2": -0.03844147881978399
      }
    },
    "420": {
      "KNN": {
        "RMSE": 7.350199540910258,
        "R2": -0.037989131726225756
      }
    },
    "421": {
      "KNN": {
        "RMSE": 7.350203485669862,
        "R2": -0.0379902458779362
      }
    },
    "422": {
      "KNN": {
        "RMSE": 7.351737807985021,
        "R2": -0.038423642810570646
      }
    },
    "423": {
      "KNN": {
        "RMSE": 7.349908540923021,
        "R2": -0.03790694379564985
      }
    },
    "424": {
      "KNN": {
        "RMSE": 7.3468698942947706,
        "R2": -0.037048924820647366
      }
    },
    "425": {
      "KNN": {
        "RMSE": 7.349115862246726,
        "R2": -0.03768308187064506
      }
    },
    "426": {
      "KNN": {
        "RMSE": 7.3503671849023355,
        "R2": -0.03803648135945803
      }
    },
    "427": {
      "KNN": {
        "RMSE": 7.351516226895081,
        "R2": -0.03836104765794812
      }
    },
    "428": {
      "KNN": {
        "RMSE": 7.352419342464043,
        "R2": -0.038616183496637424
      }
    },
    "429": {
      "KNN": {
        "RMSE": 7.351071472222858,
        "R2": -0.03823541317831336
      }
    },
    "430": {
      "KNN": {
        "RMSE": 7.350378859757488,
        "R2": -0.0380397788641631
      }
    },
    "431": {
      "KNN": {
        "RMSE": 7.346602907587857,
        "R2": -0.036973553063579745
      }
    },
    "432": {
      "KNN": {
        "RMSE": 7.34954066719597,
        "R2": -0.03780304885918162
      }
    },
    "433": {
      "KNN": {
        "RMSE": 7.3481571262869165,
        "R2": -0.037412355646933904
      }
    },
    "434": {
      "KNN": {
        "RMSE": 7.350815087336699,
        "R2": -0.03816299292576253
      }
    },
    "435": {
      "KNN": {
        "RMSE": 7.349885541240764,
        "R2": -0.037900448070584014
      }
    },
    "436": {
      "KNN": {
        "RMSE": 7.346842797567887,
        "R2": -0.03704127514668687
      }
    },
    "437": {
      "KNN": {
        "RMSE": 7.3435840929393885,
        "R2": -0.03612151632658889
      }
    },
    "438": {
      "KNN": {
        "RMSE": 7.340989903244217,
        "R2": -0.03538960641327038
      }
    },
    "439": {
      "KNN": {
        "RMSE": 7.3399822752239,
        "R2": -0.0351053897089777
      }
    },
    "440": {
      "KNN": {
        "RMSE": 7.3440928384106225,
        "R2": -0.03626508120751648
      }
    },
    "441": {
      "KNN": {
        "RMSE": 7.3469627552901775,
        "R2": -0.037075140611979585
      }
    },
    "442": {
      "KNN": {
        "RMSE": 7.348026733763037,
        "R2": -0.03737553835714369
      }
    },
    "443": {
      "KNN": {
        "RMSE": 7.349275665644576,
        "R2": -0.0377282103155856
      }
    },
    "444": {
      "KNN": {
        "RMSE": 7.346942669773919,
        "R2": -0.037069470197736765
      }
    },
    "445": {
      "KNN": {
        "RMSE": 7.346193537405731,
        "R2": -0.03685799101936049
      }
    },
    "446": {
      "KNN": {
        "RMSE": 7.346564435025731,
        "R2": -0.036962692281941045
      }
    },
    "447": {
      "KNN": {
        "RMSE": 7.346093475964315,
        "R2": -0.03682974542577
      }
    },
    "448": {
      "KNN": {
        "RMSE": 7.344096679667991,
        "R2": -0.03626616522483683
      }
    },
    "449": {
      "KNN": {
        "RMSE": 7.339567560141799,
        "R2": -0.03498842438851302
      }
    },
    "450": {
      "KNN": {
        "RMSE": 7.338066337920394,
        "R2": -0.03456507826942423
      }
    },
    "451": {
      "KNN": {
        "RMSE": 7.338252030298349,
        "R2": -0.03461743900627301
      }
    },
    "452": {
      "KNN": {
        "RMSE": 7.334869270814559,
        "R2": -0.033663790845123165
      }
    },
    "453": {
      "KNN": {
        "RMSE": 7.333630544636115,
        "R2": -0.03331468625176859
      }
    },
    "454": {
      "KNN": {
        "RMSE": 7.33467251068081,
        "R2": -0.03360833488801984
      }
    },
    "455": {
      "KNN": {
        "RMSE": 7.337379652397027,
        "R2": -0.03437146115302281
      }
    },
    "456": {
      "KNN": {
        "RMSE": 7.338956822800058,
        "R2": -0.03481618541814391
      }
    },
    "457": {
      "KNN": {
        "RMSE": 7.340991083367164,
        "R2": -0.035389939307648
      }
    },
    "458": {
      "KNN": {
        "RMSE": 7.343961466392087,
        "R2": -0.036228007869572254
      }
    },
    "459": {
      "KNN": {
        "RMSE": 7.342807724987787,
        "R2": -0.0359024491769151
      }
    },
    "460": {
      "KNN": {
        "RMSE": 7.342400171901303,
        "R2": -0.03578745950543083
      }
    },
    "461": {
      "KNN": {
        "RMSE": 7.341219347389235,
        "R2": -0.03545433005373133
      }
    },
    "462": {
      "KNN": {
        "RMSE": 7.340054918961116,
        "R2": -0.03512587866745154
      }
    },
    "463": {
      "KNN": {
        "RMSE": 7.33750781356775,
        "R2": -0.03440759596448495
      }
    },
    "464": {
      "KNN": {
        "RMSE": 7.335003347455999,
        "R2": -0.03370158059460815
      }
    }
  }
}